{"dependencies":[8,6],"downloads":32383063,"registry":{"description":"Define a non-enumerable property on an object. Uses Reflect.defineProperty when available, otherwise Object.defineProperty.","latestReleaseDate":"2018-01-26T20:24:22.283Z"},"tree":{"dependencies":[{"dependencies":[{"dependencies":[{"dependencies":[{"dependencies":[],"isLoop":false,"name":"function-bind","subtreeCount":0,"version":"1.1.2"}],"isLoop":false,"name":"hasown","subtreeCount":1,"version":"2.0.2"}],"isLoop":false,"name":"is-accessor-descriptor","subtreeCount":2,"version":"1.0.1"},{"dependencies":[{"dependencies":[{"dependencies":[],"isLoop":false,"name":"function-bind","subtreeCount":0,"version":"1.1.2"}],"isLoop":false,"name":"hasown","subtreeCount":1,"version":"2.0.2"}],"isLoop":false,"name":"is-data-descriptor","subtreeCount":2,"version":"1.0.1"}],"isLoop":false,"name":"is-descriptor","subtreeCount":6,"version":"1.0.3"},{"dependencies":[],"isLoop":false,"name":"isobject","subtreeCount":0,"version":"3.0.1"}],"isLoop":false,"name":"define-property","subtreeCount":8,"version":"2.0.2"}}